MANIFEST.in
README.rst
notifout.py
setup.py
notifout.egg-info/PKG-INFO
notifout.egg-info/SOURCES.txt
notifout.egg-info/dependency_links.txt
notifout.egg-info/requires.txt
notifout.egg-info/top_level.txt