Metadata-Version: 1.0
Name: notifout
Version: 1.1
Summary: Python API for Notifout.com
Home-page: https://github.com/pistolero/notifout-python
Author: Sergey Kirilov
Author-email: sergey.kirillov@gmail.com
License: Apache License 2.0
Keywords: python notifout
Platform: UNKNOWN
